watson_jira/__init__.py
watson_jira/cli.py
watson_jira/src/__init__.py
watson_jira/src/jira.py
watson_jira/src/watson.py
watson_jira-0.2.1.dist-info/METADATA
watson_jira-0.2.1.dist-info/WHEEL
watson_jira-0.2.1.dist-info/entry_points.txt
watson_jira-0.2.1.dist-info/top_level.txt
watson_jira-0.2.1.dist-info/RECORD
