Metadata-Version: 2.1
Name: watson-jira
Version: 0.2.1
Summary: Format and upload Watson time logs to Jira as Tempo worklogs
Home-page: http://github.com/medwig/watson-jira
Author: Jonathan Medwig
Author-email: jonmedwig@gmail.com
License: MIT
Platform: UNKNOWN
Classifier: Development Status :: 3 - Alpha
Classifier: License :: OSI Approved :: MIT License
Classifier: Programming Language :: Python :: 3.6
Classifier: Topic :: Office/Business :: Scheduling
Requires-Dist: td-watson
Requires-Dist: python-dateutil
Requires-Dist: click
Requires-Dist: simplejson
Requires-Dist: colorama
Requires-Dist: jira
